{
	"info": {
		"_postman_id": "75d11456-977a-4048-bc52-dfc8b825403b",
		"name": "Users",
		"schema": "https://schema.getpostman.com/json/collection/v2.1.0/collection.json",
		"_exporter_id": "32643953"
	},
	"item": [
		{
			"name": "LOCAL-List All Users",
			"protocolProfileBehavior": {
				"disableBodyPruning": true
			},
			"request": {
				"method": "GET",
				"header": [],
				"body": {
					"mode": "raw",
					"raw": "",
					"options": {
						"raw": {
							"language": "json"
						}
					}
				},
				"url": {
					"raw": "http://localhost:8080/users",
					"protocol": "http",
					"host": [
						"localhost"
					],
					"port": "8080",
					"path": [
						"users"
					]
				}
			},
			"response": []
		},
		{
			"name": "LOCAL-SIGNUP",
			"request": {
				"method": "POST",
				"header": [],
				"body": {
					"mode": "raw",
					"raw": "{\n  \"userEmail\": \"poncho\",\n  \"password\": \"12\"\n}",
					"options": {
						"raw": {
							"language": "json"
						}
					}
				},
				"url": {
					"raw": "http://localhost:8080/signup",
					"protocol": "http",
					"host": [
						"localhost"
					],
					"port": "8080",
					"path": [
						"signup"
					]
				}
			},
			"response": []
		},
		{
			"name": "LOCAL-SIGNIN",
			"request": {
				"method": "POST",
				"header": [],
				"body": {
					"mode": "raw",
					"raw": "{\n  \"userEmail\": \"mom\",\n  \"password\": \"dad\"\n}",
					"options": {
						"raw": {
							"language": "json"
						}
					}
				},
				"url": {
					"raw": "http://localhost:8080/signin",
					"protocol": "http",
					"host": [
						"localhost"
					],
					"port": "8080",
					"path": [
						"signin"
					]
				}
			},
			"response": []
		},
		{
			"name": "LOCAL-GET USER BY ID",
			"request": {
				"method": "GET",
				"header": [],
				"url": {
					"raw": "http://localhost:8080/users/2",
					"protocol": "http",
					"host": [
						"localhost"
					],
					"port": "8080",
					"path": [
						"users",
						"2"
					]
				}
			},
			"response": []
		},
		{
			"name": "REMOTE-SIGNIN",
			"request": {
				"method": "POST",
				"header": [],
				"body": {
					"mode": "raw",
					"raw": "{\n  \"userEmail\": \"dill\",\n  \"password\": \"p\"\n}",
					"options": {
						"raw": {
							"language": "json"
						}
					}
				},
				"url": {
					"raw": "http://coms-309-023.class.las.iastate.edu:8080/signin",
					"protocol": "http",
					"host": [
						"coms-309-023",
						"class",
						"las",
						"iastate",
						"edu"
					],
					"port": "8080",
					"path": [
						"signin"
					]
				}
			},
			"response": []
		},
		{
			"name": "REMOTE-CREATING FRIENDSHIP",
			"request": {
				"method": "POST",
				"header": [],
				"body": {
					"mode": "raw",
					"raw": "{\n    \"friendEmail1\" : \"dill\",\n    \"friendEmail2\" : \"b\"\n}",
					"options": {
						"raw": {
							"language": "json"
						}
					}
				},
				"url": {
					"raw": "http://coms-309-023.class.las.iastate.edu:8080/createFriend",
					"protocol": "http",
					"host": [
						"coms-309-023",
						"class",
						"las",
						"iastate",
						"edu"
					],
					"port": "8080",
					"path": [
						"createFriend"
					]
				}
			},
			"response": []
		},
		{
			"name": "local- creating friendship",
			"request": {
				"method": "POST",
				"header": [],
				"body": {
					"mode": "raw",
					"raw": "{\n    \"friendEmail1\" : \"mom\",\n    \"friendEmail2\" : \"march\"\n}",
					"options": {
						"raw": {
							"language": "json"
						}
					}
				},
				"url": {
					"raw": "http://localhost:8080/createFriend",
					"protocol": "http",
					"host": [
						"localhost"
					],
					"port": "8080",
					"path": [
						"createFriend"
					]
				}
			},
			"response": []
		},
		{
			"name": "getAccpetedFriends",
			"request": {
				"method": "GET",
				"header": [],
				"url": {
					"raw": "http://localhost:8080/getAcceptedFriends/mom",
					"protocol": "http",
					"host": [
						"localhost"
					],
					"port": "8080",
					"path": [
						"getAcceptedFriends",
						"mom"
					]
				}
			},
			"response": []
		},
		{
			"name": "getPendingFriends",
			"request": {
				"method": "GET",
				"header": [],
				"url": {
					"raw": "http://localhost:8080/getPendingFriends/F1",
					"protocol": "http",
					"host": [
						"localhost"
					],
					"port": "8080",
					"path": [
						"getPendingFriends",
						"F1"
					]
				}
			},
			"response": []
		},
		{
			"name": "getting one friend",
			"request": {
				"method": "GET",
				"header": [],
				"url": {
					"raw": "http://localhost:8080/friend/charles",
					"protocol": "http",
					"host": [
						"localhost"
					],
					"port": "8080",
					"path": [
						"friend",
						"charles"
					]
				}
			},
			"response": []
		},
		{
			"name": "Get User by ID",
			"request": {
				"method": "GET",
				"header": [],
				"url": {
					"raw": "http://localhost:8080/users/273",
					"protocol": "http",
					"host": [
						"localhost"
					],
					"port": "8080",
					"path": [
						"users",
						"273"
					]
				}
			},
			"response": []
		},
		{
			"name": "getUserbyEmail",
			"request": {
				"method": "GET",
				"header": [],
				"url": {
					"raw": "http://localhost:8080/getUser/big",
					"protocol": "http",
					"host": [
						"localhost"
					],
					"port": "8080",
					"path": [
						"getUser",
						"big"
					]
				}
			},
			"response": []
		}
	]
}